MANIFEST.in
README.rst
setup.py
django_lfs.egg-info/PKG-INFO
django_lfs.egg-info/SOURCES.txt
django_lfs.egg-info/dependency_links.txt
django_lfs.egg-info/not-zip-safe
django_lfs.egg-info/requires.txt
django_lfs.egg-info/top_level.txt
lfs/__init__.py
lfs/other_translations.py
lfs/plugins.py
lfs/addresses/__init__.py
lfs/addresses/forms.py
lfs/addresses/models.py
lfs/addresses/settings.py
lfs/addresses/utils.py
lfs/addresses/management/__init__.py
lfs/addresses/management/commands/__init__.py
lfs/addresses/management/commands/cleanup_addresses.py
lfs/addresses/migrations/0001_initial.py
lfs/addresses/migrations/__init__.py
lfs/caching/__init__.py
lfs/caching/apps.py
lfs/caching/listeners.py
lfs/caching/tests.py
lfs/caching/utils.py
lfs/cart/__init__.py
lfs/cart/models.py
lfs/cart/tests.py
lfs/cart/urls.py
lfs/cart/utils.py
lfs/cart/views.py
lfs/cart/management/__init__.py
lfs/cart/management/commands/__init__.py
lfs/cart/management/commands/cleanup_carts.py
lfs/cart/migrations/0001_initial.py
lfs/cart/migrations/__init__.py
lfs/catalog/__init__.py
lfs/catalog/apps.py
lfs/catalog/listeners.py
lfs/catalog/models.py
lfs/catalog/settings.py
lfs/catalog/tests.py
lfs/catalog/urls.py
lfs/catalog/utils.py
lfs/catalog/views.py
lfs/catalog/migrations/0001_initial.py
lfs/catalog/migrations/0002_auto_20150427_2206.py
lfs/catalog/migrations/0003_auto_20170214_1643.py
lfs/catalog/migrations/0004_auto_20170216_0455.py
lfs/catalog/migrations/__init__.py
lfs/checkout/__init__.py
lfs/checkout/forms.py
lfs/checkout/models.py
lfs/checkout/settings.py
lfs/checkout/urls.py
lfs/checkout/views.py
lfs/checkout/tests/__init__.py
lfs/checkout/tests/test_addresses.py
lfs/checkout/tests/test_checkout.py
lfs/core/__init__.py
lfs/core/apps.py
lfs/core/context_processors.py
lfs/core/listeners.py
lfs/core/managers.py
lfs/core/models.py
lfs/core/settings.py
lfs/core/signals.py
lfs/core/sitemap.py
lfs/core/tests.py
lfs/core/urls.py
lfs/core/utils.py
lfs/core/views.py
lfs/core/fields/__init__.py
lfs/core/fields/thumbs.py
lfs/core/fixtures/lfs_all_countries.xml
lfs/core/fixtures/lfs_shop.xml
lfs/core/fixtures/lfs_user.xml
lfs/core/management/__init__.py
lfs/core/management/commands/__init__.py
