Metadata-Version: 1.1
Name: django-lfs
Version: 0.11
Summary: LFS - Lightning Fast Shop
Home-page: http://www.getlfs.com
Author: Kai Diefenbach
Author-email: kai.diefenbach@iqpp.de
License: BSD
Keywords: django e-commerce online-shop
Platform: UNKNOWN
Classifier: Environment :: Web Environment
Classifier: Framework :: Django
Classifier: License :: OSI Approved :: BSD License
Classifier: Operating System :: OS Independent
Classifier: Programming Language :: Python
